.gitignore
LICENSE.txt
README.rst
bootstrap.py
buildout.cfg
parse_pxd.py
setup.py
stdeb.cfg
examples/cross_corr.py
examples/silly.py
examples/simple.py
ipp5_static_src/funclist.h
motmot/__init__.py
motmot.FastImage_ipp.egg-info/PKG-INFO
motmot.FastImage_ipp.egg-info/SOURCES.txt
motmot.FastImage_ipp.egg-info/dependency_links.txt
motmot.FastImage_ipp.egg-info/namespace_packages.txt
motmot.FastImage_ipp.egg-info/top_level.txt
motmot/FastImage/__init__.py
motmot/FastImage/tests.py
motmot/FastImage/util.py
src/FastImage.pxd
src/FastImage.pyx
src/FastImage_macros.h
src/ads_wrap_system.h
src/c_lib.pxd
src/c_python.pxd
src/fi_ipp.h
src/fic.c
src/fic.h
src/fic.pxd
src/fic_sobel.c
src/ipp.pxd
test_ipp/SConstruct
test_ipp/test.c
test_ipp/test3.c
test_ipp/test4.c
test_ipp/test_helpers.c
test_ipp/test_helpers.h